vrcpy/__init__.py
vrcpy/avatar.py
vrcpy/baseobject.py
vrcpy/client.py
vrcpy/enum.py
vrcpy/errors.py
vrcpy/favorite.py
vrcpy/file.py
vrcpy/moderation.py
vrcpy/notification.py
vrcpy/permission.py
vrcpy/request.py
vrcpy/user.py
vrcpy/util.py
vrcpy/world.py
vrcpy-0.8.5.dist-info/METADATA
vrcpy-0.8.5.dist-info/WHEEL
vrcpy-0.8.5.dist-info/top_level.txt
vrcpy-0.8.5.dist-info/RECORD
